gypse/__init__.py
gypse/base.py
gypse/cli.py
gypse/constants.py
gypse/extractor.py
gypse/logging.py
gypse/printer.py
gypse-0.2.dist-info/LICENSE
gypse-0.2.dist-info/METADATA
gypse-0.2.dist-info/WHEEL
gypse-0.2.dist-info/entry_points.txt
gypse-0.2.dist-info/top_level.txt
gypse-0.2.dist-info/RECORD
