Metadata-Version: 2.1
Name: gypse
Version: 0.2
Summary: Gypse analyzes and reveals information of the text files that you have. It identifies things like URLs, E-Mails and Phone Numbers, which are difficult to extract.
Home-page: https://gypse.readthedocs.org
Author: David G. Daniel
Author-email: davydany@aeroxis.com
License: MIT
Platform: UNKNOWN
Classifier: License :: OSI Approved :: MIT License
Classifier: Programming Language :: Python
Classifier: Programming Language :: Python :: 3
Classifier: Programming Language :: Python :: Implementation :: CPython
Requires-Dist: click
Requires-Dist: coloredlogs (==10.0)
Requires-Dist: humanfriendly (==4.17)
Provides-Extra: dev
Requires-Dist: bumpversion ; extra == 'dev'
Requires-Dist: click ; extra == 'dev'
Requires-Dist: coloredlogs (==10.0) ; extra == 'dev'
Requires-Dist: humanfriendly (==4.17) ; extra == 'dev'
Requires-Dist: pytest ; extra == 'dev'
Requires-Dist: pytest-cache ; extra == 'dev'
Requires-Dist: pytest-cov ; extra == 'dev'
Requires-Dist: flake8 ; extra == 'dev'
Requires-Dist: black ; extra == 'dev'
Provides-Extra: lint
Requires-Dist: flake8 ; extra == 'lint'
Requires-Dist: black ; extra == 'lint'
Provides-Extra: test
Requires-Dist: pytest ; extra == 'test'
Requires-Dist: pytest-cache ; extra == 'test'
Requires-Dist: pytest-cov ; extra == 'test'
